proctor/__init__.py
proctor/api.py
proctor/cache.py
proctor/constants.py
proctor/context_processors.py
proctor/groups.py
proctor/identify.py
proctor/lazy.py
proctor/matrix.py
proctor/middleware.py
proctor/settings.py
proctor/urls.py
proctor/static/css/proctor_default.css
proctor/templates/proctor_default_base.html
proctor/templates/proctor_groups.html
proctor/templatetags/__init__.py
proctor/templatetags/forcegroups.py
proctor/tests/__init__.py
proctor/tests/settings.py
proctor/tests/test_api.py
proctor/tests/test_context_processors.py
proctor/tests/test_groups.py
proctor/tests/test_identify.py
proctor/tests/test_lazy.py
proctor/tests/test_matrix.py
proctor/tests/test_middleware.py
proctor/tests/test_templatetags.py
proctor/tests/test_urls.py
proctor/tests/test_views.py
proctor/tests/utils.py
proctor/views/__init__.py
proctor/views/private.py
django_proctor-1.2.1.dist-info/LICENSE.txt
django_proctor-1.2.1.dist-info/METADATA
django_proctor-1.2.1.dist-info/WHEEL
django_proctor-1.2.1.dist-info/top_level.txt
django_proctor-1.2.1.dist-info/RECORD
