Metadata-Version: 2.1
Name: django-proctor
Version: 1.2.1
Summary: Django library for interacting with the Proctor A/B testing framework
Home-page: https://github.com/indeedeng/django-proctor
License: Apache
Platform: UNKNOWN
Classifier: Development Status :: 5 - Production/Stable
Classifier: Intended Audience :: Developers
Classifier: Environment :: Web Environment
Classifier: Framework :: Django
Classifier: Framework :: Django :: 1.11
Classifier: Framework :: Django :: 2.0
Classifier: Framework :: Django :: 2.1
Classifier: Framework :: Django :: 2.2
Classifier: License :: OSI Approved :: Apache Software License
Classifier: Programming Language :: Python :: 2
Classifier: Programming Language :: Python :: 2.7
Classifier: Programming Language :: Python :: 3
Classifier: Programming Language :: Python :: 3.6
License-File: LICENSE.txt
Requires-Dist: Django
Requires-Dist: ndg-httpsclient
Requires-Dist: pyOpenSSL
Requires-Dist: requests
Requires-Dist: tenacity (>=4.8.0)
